fucciphase/__init__.py
fucciphase/__main__.py
fucciphase/fucci_phase.py
fucciphase/io.py
fucciphase/main_cli.py
fucciphase/phase.py
fucciphase/plot.py
fucciphase/py.typed
fucciphase/sensor.py
fucciphase/tracking_utilities.py
fucciphase/napari/__init__.py
fucciphase/napari/tracks_to_napari.py
fucciphase/utils/__init__.py
fucciphase/utils/checks.py
fucciphase/utils/dtw.py
fucciphase/utils/normalize.py
fucciphase/utils/phase_fit.py
fucciphase/utils/simulator.py
fucciphase/utils/track_postprocessing.py
fucciphase/utils/trackmate.py
fucciphase-0.0.3.dist-info/METADATA
fucciphase-0.0.3.dist-info/WHEEL
fucciphase-0.0.3.dist-info/entry_points.txt
fucciphase-0.0.3.dist-info/licenses/LICENSE
fucciphase-0.0.3.dist-info/RECORD
