Metadata-Version: 2.4
Name: fucciphase
Version: 0.0.3
Summary: Cell cycle analysis plugin.
Project-URL: homepage, https://github.com/nobias-ht/fucciphase
Project-URL: repository, https://github.com/nobias-ht/fucciphase
Author-email: Joran Deschamps <joran.deschamps@fht.org>
License: BSD-3-Clause
License-File: LICENSE
Classifier: Development Status :: 3 - Alpha
Classifier: License :: OSI Approved :: BSD License
Classifier: Programming Language :: Python :: 3
Classifier: Programming Language :: Python :: 3.10
Classifier: Programming Language :: Python :: 3.11
Classifier: Programming Language :: Python :: 3.12
Classifier: Programming Language :: Python :: 3.13
Classifier: Programming Language :: Python :: 3.14
Requires-Python: >=3.8
Requires-Dist: dtaidistance
Requires-Dist: lineagetree<1.5.0
Requires-Dist: matplotlib
Requires-Dist: monotonic-derivative
Requires-Dist: numpy
Requires-Dist: openpyxl
Requires-Dist: pandas
Requires-Dist: scipy
Requires-Dist: svgwrite
Provides-Extra: dev
Requires-Dist: ipython; extra == 'dev'
Requires-Dist: mypy; extra == 'dev'
Requires-Dist: pdbpp; extra == 'dev'
Requires-Dist: pre-commit; extra == 'dev'
Requires-Dist: rich; extra == 'dev'
Requires-Dist: ruff; extra == 'dev'
Provides-Extra: doc
Requires-Dist: sphinx; extra == 'doc'
Provides-Extra: jupyter
Requires-Dist: jupyter; extra == 'jupyter'
Provides-Extra: napari
Requires-Dist: bioio; extra == 'napari'
Requires-Dist: bioio-ome-tiff; extra == 'napari'
Requires-Dist: bioio-tifffile; extra == 'napari'
Requires-Dist: napari; extra == 'napari'
Provides-Extra: test
Requires-Dist: pytest; extra == 'test'
Requires-Dist: pytest-cov; extra == 'test'
